<annotation>
    <filename>SPRVsTOE_BO3_1_238.jpg</filename>
    <version>v3.0</version>
    <review_status>passed</review_status>
    <time_elapsed>151</time_elapsed>
    <img_label/>
    <size>
        <width>1920</width>
        <height>1080</height>
    </size>
    <padding_pxt>
        <padding_x>76</padding_x>
        <padding_y>43</padding_y>
    </padding_pxt>
    <object>
        <name>armor</name>
        <armor_class>1</armor_class>
        <armor_color>grey</armor_color>
        <generated>0</generated>
        <is_incorrect>0</is_incorrect>
        <bndbox>
            <xmin>813.709</xmin>
            <ymin>836.57</ymin>
            <xmax>847.928</xmax>
            <ymax>868.254</ymax>
        </bndbox>
    </object>
    <object>
        <name>armor</name>
        <armor_class>4</armor_class>
        <armor_color>grey</armor_color>
        <generated>0</generated>
        <is_incorrect>0</is_incorrect>
        <bndbox>
            <xmin>1363.76</xmin>
            <ymin>716.167</ymin>
            <xmax>1397.98</xmax>
            <ymax>737.713</ymax>
        </bndbox>
    </object>
    <object>
        <name>armor</name>
        <armor_class>4</armor_class>
        <armor_color>blue</armor_color>
        <generated>0</generated>
        <is_incorrect>0</is_incorrect>
        <bndbox>
            <xmin>500.663</xmin>
            <ymin>782.072</ymin>
            <xmax>534.883</xmax>
            <ymax>808.687</ymax>
        </bndbox>
    </object>
    <object>
        <name>armor</name>
        <armor_class>none</armor_class>
        <armor_color>red</armor_color>
        <generated>0</generated>
        <is_incorrect>0</is_incorrect>
        <bndbox>
            <xmin>814.976</xmin>
            <ymin>425.935</ymin>
            <xmax>830.185</xmax>
            <ymax>456.352</ymax>
        </bndbox>
    </object>
    <object>
        <name>armor</name>
        <armor_class>8</armor_class>
        <armor_color>red</armor_color>
        <generated>0</generated>
        <is_incorrect>0</is_incorrect>
        <bndbox>
            <xmin>384.063</xmin>
            <ymin>399.32</ymin>
            <xmax>436.026</xmax>
            <ymax>424.667</ymax>
        </bndbox>
    </object>
    <object>
        <name>watcher</name>
        <difficulty>1</difficulty>
        <generated>0</generated>
        <is_incorrect>0</is_incorrect>
        <bndbox>
            <xmin>813.709</xmin>
            <ymin>410.726</ymin>
            <xmax>907.496</xmax>
            <ymax>522.257</ymax>
        </bndbox>
    </object>
    <object>
        <name>armor</name>
        <armor_class>6</armor_class>
        <armor_color>red</armor_color>
        <generated>0</generated>
        <is_incorrect>0</is_incorrect>
        <bndbox>
            <xmin>449.967</xmin>
            <ymin>417.063</ymin>
            <xmax>481.652</xmax>
            <ymax>499.443</ymax>
        </bndbox>
    </object>
    <object>
        <name>armor</name>
        <armor_class>6</armor_class>
        <armor_color>red</armor_color>
        <generated>0</generated>
        <is_incorrect>0</is_incorrect>
        <bndbox>
            <xmin>403.074</xmin>
            <ymin>424.667</ymin>
            <xmax>417.015</xmax>
            <ymax>490.572</ymax>
        </bndbox>
    </object>
    <object>
        <name>armor</name>
        <armor_class>6</armor_class>
        <armor_color>red</armor_color>
        <generated>0</generated>
        <is_incorrect>0</is_incorrect>
        <bndbox>
            <xmin>343.507</xmin>
            <ymin>417.063</ymin>
            <xmax>375.191</xmax>
            <ymax>489.304</ymax>
        </bndbox>
    </object>
    <object>
        <name>base</name>
        <difficulty>0</difficulty>
        <generated>0</generated>
        <is_incorrect>0</is_incorrect>
        <bndbox>
            <xmin>304.217</xmin>
            <ymin>394.25</ymin>
            <xmax>527.278</xmax>
            <ymax>584.359</ymax>
        </bndbox>
    </object>
    <object>
        <name>car</name>
        <difficulty>1</difficulty>
        <generated>0</generated>
        <is_incorrect>0</is_incorrect>
        <bndbox>
            <xmin>702.178</xmin>
            <ymin>733.911</ymin>
            <xmax>883.415</xmax>
            <ymax>893.602</ymax>
        </bndbox>
    </object>
    <object>
        <name>car</name>
        <difficulty>0</difficulty>
        <generated>0</generated>
        <is_incorrect>0</is_incorrect>
        <bndbox>
            <xmin>1339.68</xmin>
            <ymin>651.53</ymin>
            <xmax>1442.33</xmax>
            <ymax>759.259</ymax>
        </bndbox>
    </object>
    <object>
        <name>car</name>
        <difficulty>0</difficulty>
        <generated>0</generated>
        <is_incorrect>0</is_incorrect>
        <bndbox>
            <xmin>466.443</xmin>
            <ymin>704.761</ymin>
            <xmax>628.67</xmax>
            <ymax>816.291</ymax>
        </bndbox>
    </object>
</annotation>
