<annotation>
    <filename>TDTVsI Hiter_BO5_4_118.jpg</filename>
    <version>v3.0</version>
    <review_status>passed</review_status>
    <time_elapsed>920</time_elapsed>
    <img_label/>
    <size>
        <width>1920</width>
        <height>1080</height>
    </size>
    <padding_pxt>
        <padding_x>76</padding_x>
        <padding_y>43</padding_y>
    </padding_pxt>
    <object>
        <name>ignore</name>
        <generated>0</generated>
        <is_incorrect>0</is_incorrect>
        <bndbox>
            <xmin>750.339</xmin>
            <ymin>174.991</ymin>
            <xmax>782.024</xmax>
            <ymax>202.874</ymax>
        </bndbox>
    </object>
    <object>
        <name>ignore</name>
        <generated>0</generated>
        <is_incorrect>0</is_incorrect>
        <bndbox>
            <xmin>828.917</xmin>
            <ymin>183.863</ymin>
            <xmax>860.602</xmax>
            <ymax>218.083</ymax>
        </bndbox>
    </object>
    <object>
        <name>ignore</name>
        <generated>0</generated>
        <is_incorrect>0</is_incorrect>
        <bndbox>
            <xmin>1007.62</xmin>
            <ymin>117.959</ymin>
            <xmax>1032.97</xmax>
            <ymax>147.109</ymax>
        </bndbox>
    </object>
    <object>
        <name>ignore</name>
        <generated>0</generated>
        <is_incorrect>0</is_incorrect>
        <bndbox>
            <xmin>1055.78</xmin>
            <ymin>173.724</ymin>
            <xmax>1079.86</xmax>
            <ymax>195.27</ymax>
        </bndbox>
    </object>
    <object>
        <name>ignore</name>
        <generated>0</generated>
        <is_incorrect>0</is_incorrect>
        <bndbox>
            <xmin>823.848</xmin>
            <ymin>71.0652</ymin>
            <xmax>840.324</xmax>
            <ymax>87.5413</ymax>
        </bndbox>
    </object>
    <object>
        <name>ignore</name>
        <generated>0</generated>
        <is_incorrect>0</is_incorrect>
        <bndbox>
            <xmin>1069.72</xmin>
            <ymin>130.633</ymin>
            <xmax>1088.73</xmax>
            <ymax>148.376</ymax>
        </bndbox>
    </object>
    <object>
        <name>ignore</name>
        <generated>0</generated>
        <is_incorrect>0</is_incorrect>
        <bndbox>
            <xmin>1088.73</xmin>
            <ymin>85.0065</ymin>
            <xmax>1105.21</xmax>
            <ymax>98.9478</ymax>
        </bndbox>
    </object>
    <object>
        <name>ignore</name>
        <generated>0</generated>
        <is_incorrect>0</is_incorrect>
        <bndbox>
            <xmin>1168.58</xmin>
            <ymin>77.4022</ymin>
            <xmax>1199</xmax>
            <ymax>107.82</ymax>
        </bndbox>
    </object>
    <object>
        <name>armor</name>
        <armor_class>7</armor_class>
        <armor_color>blue</armor_color>
        <generated>0</generated>
        <is_incorrect>0</is_incorrect>
        <bndbox>
            <xmin>1594.42</xmin>
            <ymin>494.374</ymin>
            <xmax>1619.77</xmax>
            <ymax>504.513</ymax>
        </bndbox>
    </object>
    <object>
        <name>watcher</name>
        <difficulty>0</difficulty>
        <generated>0</generated>
        <is_incorrect>0</is_incorrect>
        <bndbox>
            <xmin>1580.48</xmin>
            <ymin>472.828</ymin>
            <xmax>1628.64</xmax>
            <ymax>526.059</ymax>
        </bndbox>
    </object>
    <object>
        <name>armor</name>
        <armor_class>6</armor_class>
        <armor_color>blue</armor_color>
        <generated>0</generated>
        <is_incorrect>0</is_incorrect>
        <bndbox>
            <xmin>1893.53</xmin>
            <ymin>470.293</ymin>
            <xmax>1921.41</xmax>
            <ymax>509.583</ymax>
        </bndbox>
    </object>
    <object>
        <name>base</name>
        <difficulty>2</difficulty>
        <generated>0</generated>
        <is_incorrect>0</is_incorrect>
        <bndbox>
            <xmin>1869.45</xmin>
            <ymin>465.224</ymin>
            <xmax>1961.97</xmax>
            <ymax>552.674</ymax>
        </bndbox>
    </object>
    <object>
        <name>armor</name>
        <armor_class>2</armor_class>
        <armor_color>red</armor_color>
        <generated>0</generated>
        <is_incorrect>0</is_incorrect>
        <bndbox>
            <xmin>614.728</xmin>
            <ymin>746.585</ymin>
            <xmax>632.472</xmax>
            <ymax>760.526</ymax>
        </bndbox>
    </object>
    <object>
        <name>armor</name>
        <armor_class>2</armor_class>
        <armor_color>red</armor_color>
        <generated>0</generated>
        <is_incorrect>0</is_incorrect>
        <bndbox>
            <xmin>557.696</xmin>
            <ymin>754.189</ymin>
            <xmax>574.172</xmax>
            <ymax>770.665</ymax>
        </bndbox>
    </object>
    <object>
        <name>armor</name>
        <armor_class>1</armor_class>
        <armor_color>red</armor_color>
        <generated>0</generated>
        <is_incorrect>0</is_incorrect>
        <bndbox>
            <xmin>304.217</xmin>
            <ymin>730.109</ymin>
            <xmax>319.426</xmax>
            <ymax>746.585</ymax>
        </bndbox>
    </object>
    <object>
        <name>armor</name>
        <armor_class>1</armor_class>
        <armor_color>red</armor_color>
        <generated>0</generated>
        <is_incorrect>0</is_incorrect>
        <bndbox>
            <xmin>320.693</xmin>
            <ymin>738.98</ymin>
            <xmax>334.635</xmax>
            <ymax>755.457</ymax>
        </bndbox>
    </object>
    <object>
        <name>armor</name>
        <armor_class>1</armor_class>
        <armor_color>red</armor_color>
        <generated>0</generated>
        <is_incorrect>0</is_incorrect>
        <bndbox>
            <xmin>268.73</xmin>
            <ymin>754.189</ymin>
            <xmax>305.485</xmax>
            <ymax>770.665</ymax>
        </bndbox>
    </object>
    <object>
        <name>armor</name>
        <armor_class>3</armor_class>
        <armor_color>red</armor_color>
        <generated>0</generated>
        <is_incorrect>0</is_incorrect>
        <bndbox>
            <xmin>507</xmin>
            <ymin>1052.03</ymin>
            <xmax>527.278</xmax>
            <ymax>1074.84</ymax>
        </bndbox>
    </object>
    <object>
        <name>armor</name>
        <armor_class>1</armor_class>
        <armor_color>blue</armor_color>
        <generated>0</generated>
        <is_incorrect>0</is_incorrect>
        <bndbox>
            <xmin>1532.32</xmin>
            <ymin>728.841</ymin>
            <xmax>1551.33</xmax>
            <ymax>745.317</ymax>
        </bndbox>
    </object>
    <object>
        <name>armor</name>
        <armor_class>1</armor_class>
        <armor_color>blue</armor_color>
        <generated>0</generated>
        <is_incorrect>0</is_incorrect>
        <bndbox>
            <xmin>1484.16</xmin>
            <ymin>736.446</ymin>
            <xmax>1508.24</xmax>
            <ymax>752.922</ymax>
        </bndbox>
    </object>
    <object>
        <name>armor</name>
        <armor_class>4</armor_class>
        <armor_color>red</armor_color>
        <generated>0</generated>
        <is_incorrect>0</is_incorrect>
        <bndbox>
            <xmin>520.941</xmin>
            <ymin>513.385</ymin>
            <xmax>532.348</xmax>
            <ymax>520.989</ymax>
        </bndbox>
    </object>
    <object>
        <name>armor</name>
        <armor_class>4</armor_class>
        <armor_color>red</armor_color>
        <generated>0</generated>
        <is_incorrect>0</is_incorrect>
        <bndbox>
            <xmin>512.07</xmin>
            <ymin>522.257</ymin>
            <xmax>529.813</xmax>
            <ymax>533.663</ymax>
        </bndbox>
    </object>
    <object>
        <name>armor</name>
        <armor_class>4</armor_class>
        <armor_color>red</armor_color>
        <generated>0</generated>
        <is_incorrect>0</is_incorrect>
        <bndbox>
            <xmin>487.989</xmin>
            <ymin>520.989</ymin>
            <xmax>500.663</xmax>
            <ymax>534.93</ymax>
        </bndbox>
    </object>
    <object>
        <name>armor</name>
        <armor_class>2</armor_class>
        <armor_color>blue</armor_color>
        <generated>0</generated>
        <is_incorrect>0</is_incorrect>
        <bndbox>
            <xmin>1324.47</xmin>
            <ymin>616.043</ymin>
            <xmax>1333.34</xmax>
            <ymax>631.252</ymax>
        </bndbox>
    </object>
    <object>
        <name>armor</name>
        <armor_class>2</armor_class>
        <armor_color>blue</armor_color>
        <generated>0</generated>
        <is_incorrect>0</is_incorrect>
        <bndbox>
            <xmin>1281.38</xmin>
            <ymin>621.113</ymin>
            <xmax>1301.65</xmax>
            <ymax>636.322</ymax>
        </bndbox>
    </object>
    <object>
        <name>armor</name>
        <armor_class>3</armor_class>
        <armor_color>blue</armor_color>
        <generated>0</generated>
        <is_incorrect>0</is_incorrect>
        <bndbox>
            <xmin>1548.8</xmin>
            <ymin>637.589</ymin>
            <xmax>1565.27</xmax>
            <ymax>650.263</ymax>
        </bndbox>
    </object>
    <object>
        <name>armor</name>
        <armor_class>3</armor_class>
        <armor_color>blue</armor_color>
        <generated>0</generated>
        <is_incorrect>0</is_incorrect>
        <bndbox>
            <xmin>1522.18</xmin>
            <ymin>627.45</ymin>
            <xmax>1542.46</xmax>
            <ymax>636.322</ymax>
        </bndbox>
    </object>
    <object>
        <name>armor</name>
        <armor_class>3</armor_class>
        <armor_color>blue</armor_color>
        <generated>0</generated>
        <is_incorrect>0</is_incorrect>
        <bndbox>
            <xmin>1514.58</xmin>
            <ymin>637.589</ymin>
            <xmax>1531.05</xmax>
            <ymax>648.996</ymax>
        </bndbox>
    </object>
    <object>
        <name>car</name>
        <difficulty>1</difficulty>
        <generated>0</generated>
        <is_incorrect>0</is_incorrect>
        <bndbox>
            <xmin>428.422</xmin>
            <ymin>1027.95</ymin>
            <xmax>546.289</xmax>
            <ymax>1115.4</ymax>
        </bndbox>
    </object>
    <object>
        <name>car</name>
        <difficulty>0</difficulty>
        <generated>0</generated>
        <is_incorrect>0</is_incorrect>
        <bndbox>
            <xmin>484.187</xmin>
            <ymin>495.641</ymin>
            <xmax>541.22</xmax>
            <ymax>548.872</ymax>
        </bndbox>
    </object>
    <object>
        <name>car</name>
        <difficulty>0</difficulty>
        <generated>0</generated>
        <is_incorrect>0</is_incorrect>
        <bndbox>
            <xmin>226.907</xmin>
            <ymin>676.878</ymin>
            <xmax>335.902</xmax>
            <ymax>783.339</ymax>
        </bndbox>
    </object>
    <object>
        <name>car</name>
        <difficulty>0</difficulty>
        <generated>0</generated>
        <is_incorrect>0</is_incorrect>
        <bndbox>
            <xmin>527.278</xmin>
            <ymin>683.215</ymin>
            <xmax>645.146</xmax>
            <ymax>804.885</ymax>
        </bndbox>
    </object>
    <object>
        <name>car</name>
        <difficulty>0</difficulty>
        <generated>0</generated>
        <is_incorrect>0</is_incorrect>
        <bndbox>
            <xmin>1249.69</xmin>
            <ymin>571.685</ymin>
            <xmax>1334.61</xmax>
            <ymax>664.204</ymax>
        </bndbox>
    </object>
    <object>
        <name>car</name>
        <difficulty>0</difficulty>
        <generated>0</generated>
        <is_incorrect>0</is_incorrect>
        <bndbox>
            <xmin>1504.44</xmin>
            <ymin>608.439</ymin>
            <xmax>1579.21</xmax>
            <ymax>661.67</ymax>
        </bndbox>
    </object>
    <object>
        <name>car</name>
        <difficulty>0</difficulty>
        <generated>0</generated>
        <is_incorrect>0</is_incorrect>
        <bndbox>
            <xmin>1460.08</xmin>
            <ymin>680.68</ymin>
            <xmax>1570.34</xmax>
            <ymax>764.328</ymax>
        </bndbox>
    </object>
</annotation>
