<annotation>
    <filename>TDTVsI Hiter_BO5_4_341.jpg</filename>
    <version>v3.0</version>
    <review_status>passed</review_status>
    <time_elapsed>10620</time_elapsed>
    <img_label/>
    <size>
        <width>1920</width>
        <height>1080</height>
    </size>
    <padding_pxt>
        <padding_x>76</padding_x>
        <padding_y>43</padding_y>
    </padding_pxt>
    <object>
        <name>watcher</name>
        <difficulty>1</difficulty>
        <generated>0</generated>
        <is_incorrect>0</is_incorrect>
        <bndbox>
            <xmin>289.009</xmin>
            <ymin>457.62</ymin>
            <xmax>381.528</xmax>
            <ymax>561.546</ymax>
        </bndbox>
    </object>
    <object>
        <name>armor</name>
        <armor_class>2</armor_class>
        <armor_color>red</armor_color>
        <generated>0</generated>
        <is_incorrect>0</is_incorrect>
        <bndbox>
            <xmin>1171.11</xmin>
            <ymin>576.754</ymin>
            <xmax>1197.73</xmax>
            <ymax>599.567</ymax>
        </bndbox>
    </object>
    <object>
        <name>armor</name>
        <armor_class>2</armor_class>
        <armor_color>red</armor_color>
        <generated>0</generated>
        <is_incorrect>0</is_incorrect>
        <bndbox>
            <xmin>1086.2</xmin>
            <ymin>576.754</ymin>
            <xmax>1112.81</xmax>
            <ymax>603.37</ymax>
        </bndbox>
    </object>
    <object>
        <name>armor</name>
        <armor_class>3</armor_class>
        <armor_color>blue</armor_color>
        <generated>0</generated>
        <is_incorrect>0</is_incorrect>
        <bndbox>
            <xmin>1043.11</xmin>
            <ymin>627.45</ymin>
            <xmax>1068.45</xmax>
            <ymax>654.065</ymax>
        </bndbox>
    </object>
    <object>
        <name>armor</name>
        <armor_class>3</armor_class>
        <armor_color>blue</armor_color>
        <generated>0</generated>
        <is_incorrect>0</is_incorrect>
        <bndbox>
            <xmin>986.074</xmin>
            <ymin>607.172</ymin>
            <xmax>1030.43</xmax>
            <ymax>628.717</ymax>
        </bndbox>
    </object>
    <object>
        <name>armor</name>
        <armor_class>3</armor_class>
        <armor_color>blue</armor_color>
        <generated>0</generated>
        <is_incorrect>0</is_incorrect>
        <bndbox>
            <xmin>982.272</xmin>
            <ymin>629.985</ymin>
            <xmax>1007.62</xmax>
            <ymax>655.333</ymax>
        </bndbox>
    </object>
    <object>
        <name>armor</name>
        <armor_class>2</armor_class>
        <armor_color>blue</armor_color>
        <generated>0</generated>
        <is_incorrect>0</is_incorrect>
        <bndbox>
            <xmin>1003.82</xmin>
            <ymin>504.513</ymin>
            <xmax>1039.3</xmax>
            <ymax>527.326</ymax>
        </bndbox>
    </object>
    <object>
        <name>car</name>
        <difficulty>1</difficulty>
        <generated>0</generated>
        <is_incorrect>0</is_incorrect>
        <bndbox>
            <xmin>467.711</xmin>
            <ymin>262.441</ymin>
            <xmax>589.38</xmax>
            <ymax>376.507</ymax>
        </bndbox>
    </object>
    <object>
        <name>car</name>
        <difficulty>0</difficulty>
        <generated>0</generated>
        <is_incorrect>0</is_incorrect>
        <bndbox>
            <xmin>958.191</xmin>
            <ymin>417.063</ymin>
            <xmax>1092.53</xmax>
            <ymax>569.15</ymax>
        </bndbox>
    </object>
    <object>
        <name>car</name>
        <difficulty>0</difficulty>
        <generated>0</generated>
        <is_incorrect>0</is_incorrect>
        <bndbox>
            <xmin>1058.32</xmin>
            <ymin>479.165</ymin>
            <xmax>1235.75</xmax>
            <ymax>659.135</ymax>
        </bndbox>
    </object>
    <object>
        <name>car</name>
        <difficulty>0</difficulty>
        <generated>0</generated>
        <is_incorrect>0</is_incorrect>
        <bndbox>
            <xmin>956.924</xmin>
            <ymin>569.15</ymin>
            <xmax>1093.8</xmax>
            <ymax>675.611</ymax>
        </bndbox>
    </object>
</annotation>
