<annotation>
    <filename>TDTVsI Hiter_BO5_4_330.jpg</filename>
    <version>v3.0</version>
    <review_status>passed</review_status>
    <time_elapsed>10669</time_elapsed>
    <img_label/>
    <size>
        <width>1920</width>
        <height>1080</height>
    </size>
    <padding_pxt>
        <padding_x>76</padding_x>
        <padding_y>43</padding_y>
    </padding_pxt>
    <object>
        <name>armor</name>
        <armor_class>7</armor_class>
        <armor_color>red</armor_color>
        <generated>0</generated>
        <is_incorrect>0</is_incorrect>
        <bndbox>
            <xmin>475.315</xmin>
            <ymin>559.011</ymin>
            <xmax>539.952</xmax>
            <ymax>585.626</ymax>
        </bndbox>
    </object>
    <object>
        <name>watcher</name>
        <difficulty>0</difficulty>
        <generated>0</generated>
        <is_incorrect>0</is_incorrect>
        <bndbox>
            <xmin>467.711</xmin>
            <ymin>496.909</ymin>
            <xmax>562.765</xmax>
            <ymax>610.974</ymax>
        </bndbox>
    </object>
    <object>
        <name>armor</name>
        <armor_class>none</armor_class>
        <armor_color>red</armor_color>
        <generated>0</generated>
        <is_incorrect>0</is_incorrect>
        <bndbox>
            <xmin>1752.85</xmin>
            <ymin>418.33</ymin>
            <xmax>1788.33</xmax>
            <ymax>443.678</ymax>
        </bndbox>
    </object>
    <object>
        <name>armor</name>
        <armor_class>4</armor_class>
        <armor_color>red</armor_color>
        <generated>0</generated>
        <is_incorrect>0</is_incorrect>
        <bndbox>
            <xmin>1248.42</xmin>
            <ymin>470.293</ymin>
            <xmax>1268.7</xmax>
            <ymax>493.107</ymax>
        </bndbox>
    </object>
    <object>
        <name>armor</name>
        <armor_class>none</armor_class>
        <armor_color>red</armor_color>
        <generated>0</generated>
        <is_incorrect>0</is_incorrect>
        <bndbox>
            <xmin>313.089</xmin>
            <ymin>902.474</ymin>
            <xmax>376.459</xmax>
            <ymax>939.228</ymax>
        </bndbox>
    </object>
    <object>
        <name>armor</name>
        <armor_class>none</armor_class>
        <armor_color>red</armor_color>
        <generated>0</generated>
        <is_incorrect>0</is_incorrect>
        <bndbox>
            <xmin>348.576</xmin>
            <ymin>934.159</ymin>
            <xmax>395.47</xmax>
            <ymax>969.646</ymax>
        </bndbox>
    </object>
    <object>
        <name>armor</name>
        <armor_class>none</armor_class>
        <armor_color>red</armor_color>
        <generated>0</generated>
        <is_incorrect>0</is_incorrect>
        <bndbox>
            <xmin>256.057</xmin>
            <ymin>934.159</ymin>
            <xmax>311.822</xmax>
            <ymax>968.378</ymax>
        </bndbox>
    </object>
    <object>
        <name>armor</name>
        <armor_class>1</armor_class>
        <armor_color>blue</armor_color>
        <generated>0</generated>
        <is_incorrect>0</is_incorrect>
        <bndbox>
            <xmin>1003.82</xmin>
            <ymin>571.685</ymin>
            <xmax>1029.17</xmax>
            <ymax>595.765</ymax>
        </bndbox>
    </object>
    <object>
        <name>armor</name>
        <armor_class>1</armor_class>
        <armor_color>blue</armor_color>
        <generated>0</generated>
        <is_incorrect>0</is_incorrect>
        <bndbox>
            <xmin>923.972</xmin>
            <ymin>576.754</ymin>
            <xmax>974.667</xmax>
            <ymax>593.23</ymax>
        </bndbox>
    </object>
    <object>
        <name>armor</name>
        <armor_class>1</armor_class>
        <armor_color>grey</armor_color>
        <generated>0</generated>
        <is_incorrect>0</is_incorrect>
        <bndbox>
            <xmin>917.635</xmin>
            <ymin>599.567</ymin>
            <xmax>965.796</xmax>
            <ymax>623.648</ymax>
        </bndbox>
    </object>
    <object>
        <name>armor</name>
        <armor_class>3</armor_class>
        <armor_color>blue</armor_color>
        <generated>0</generated>
        <is_incorrect>0</is_incorrect>
        <bndbox>
            <xmin>1338.41</xmin>
            <ymin>490.572</ymin>
            <xmax>1371.36</xmax>
            <ymax>513.385</ymax>
        </bndbox>
    </object>
    <object>
        <name>armor</name>
        <armor_class>3</armor_class>
        <armor_color>blue</armor_color>
        <generated>0</generated>
        <is_incorrect>0</is_incorrect>
        <bndbox>
            <xmin>1297.85</xmin>
            <ymin>479.165</ymin>
            <xmax>1318.13</xmax>
            <ymax>501.978</ymax>
        </bndbox>
    </object>
    <object>
        <name>armor</name>
        <armor_class>2</armor_class>
        <armor_color>blue</armor_color>
        <generated>0</generated>
        <is_incorrect>0</is_incorrect>
        <bndbox>
            <xmin>1190.12</xmin>
            <ymin>514.652</ymin>
            <xmax>1224.34</xmax>
            <ymax>536.198</ymax>
        </bndbox>
    </object>
    <object>
        <name>armor</name>
        <armor_class>2</armor_class>
        <armor_color>blue</armor_color>
        <generated>0</generated>
        <is_incorrect>0</is_incorrect>
        <bndbox>
            <xmin>1110.28</xmin>
            <ymin>509.583</ymin>
            <xmax>1133.09</xmax>
            <ymax>532.396</ymax>
        </bndbox>
    </object>
    <object>
        <name>car</name>
        <difficulty>0</difficulty>
        <generated>0</generated>
        <is_incorrect>0</is_incorrect>
        <bndbox>
            <xmin>221.837</xmin>
            <ymin>846.709</ymin>
            <xmax>409.411</xmax>
            <ymax>1000.06</ymax>
        </bndbox>
    </object>
    <object>
        <name>car</name>
        <difficulty>0</difficulty>
        <generated>0</generated>
        <is_incorrect>0</is_incorrect>
        <bndbox>
            <xmin>879.613</xmin>
            <ymin>503.246</ymin>
            <xmax>1046.91</xmax>
            <ymax>635.054</ymax>
        </bndbox>
    </object>
    <object>
        <name>car</name>
        <difficulty>0</difficulty>
        <generated>0</generated>
        <is_incorrect>0</is_incorrect>
        <bndbox>
            <xmin>1283.91</xmin>
            <ymin>434.807</ymin>
            <xmax>1395.44</xmax>
            <ymax>529.861</ymax>
        </bndbox>
    </object>
    <object>
        <name>car</name>
        <difficulty>0</difficulty>
        <generated>0</generated>
        <is_incorrect>0</is_incorrect>
        <bndbox>
            <xmin>1076.06</xmin>
            <ymin>418.33</ymin>
            <xmax>1266.17</xmax>
            <ymax>593.23</ymax>
        </bndbox>
    </object>
    <object>
        <name>car</name>
        <difficulty>2</difficulty>
        <generated>0</generated>
        <is_incorrect>0</is_incorrect>
        <bndbox>
            <xmin>1172.38</xmin>
            <ymin>413.261</ymin>
            <xmax>1277.57</xmax>
            <ymax>517.187</ymax>
        </bndbox>
    </object>
    <object>
        <name>car</name>
        <difficulty>1</difficulty>
        <generated>0</generated>
        <is_incorrect>0</is_incorrect>
        <bndbox>
            <xmin>1737.64</xmin>
            <ymin>335.95</ymin>
            <xmax>1884.65</xmax>
            <ymax>471.561</ymax>
        </bndbox>
    </object>
</annotation>
